{
  "main": {
    "id": "0a9b12ec42147252",
    "type": "split",
    "children": [
      {
        "id": "6d0f47d451af85d9",
        "type": "tabs",
        "children": [
          {
            "id": "fe4008cfb4e5ff88",
            "type": "leaf",
            "state": {
              "type": "markdown",
              "state": {
                "file": "development/python/╣╪╙┌▒╚╚№/Getting a token through the API.md",
                "mode": "source",
                "source": false
              }
            }
          }
        ]
      }
    ],
    "direction": "vertical"
  },
  "left": {
    "id": "8d0f0f24beddf0f2",
    "type": "split",
    "children": [
      {
        "id": "9a048c754f151bf7",
        "type": "tabs",
        "children": [
          {
            "id": "fbc2397c280a0126",
            "type": "leaf",
            "state": {
              "type": "file-explorer",
              "state": {
                "sortOrder": "alphabetical"
              }
            }
          },
          {
            "id": "8eeb372101b937d2",
            "type": "leaf",
            "state": {
              "type": "search",
              "state": {
                "query": "",
                "matchingCase": false,
                "explainSearch": false,
                "collapseAll": false,
                "extraContext": false,
                "sortOrder": "alphabetical"
              }
            }
          },
          {
            "id": "55d74c90beaab351",
            "type": "leaf",
            "state": {
              "type": "bookmarks",
              "state": {}
            }
          }
        ]
      }
    ],
    "direction": "horizontal",
    "width": 300
  },
  "right": {
    "id": "432ea56d3bf02647",
    "type": "split",
    "children": [
      {
        "id": "2cccfe563566f4ee",
        "type": "tabs",
        "children": [
          {
            "id": "8ac09741003189f9",
            "type": "leaf",
            "state": {
              "type": "backlink",
              "state": {
                "file": "development/python/╣╪╙┌▒╚╚№/Getting a token through the API.md",
                "collapseAll": false,
                "extraContext": false,
                "sortOrder": "alphabetical",
                "showSearch": false,
                "searchQuery": "",
                "backlinkCollapsed": false,
                "unlinkedCollapsed": true
              }
            }
          },
          {
            "id": "e34eb98b272e8b8f",
            "type": "leaf",
            "state": {
              "type": "outgoing-link",
              "state": {
                "file": "development/python/╣╪╙┌▒╚╚№/Getting a token through the API.md",
                "linksCollapsed": false,
                "unlinkedCollapsed": true
              }
            }
          },
          {
            "id": "f2f77d906392d0a2",
            "type": "leaf",
            "state": {
              "type": "tag",
              "state": {
                "sortOrder": "frequency",
                "useHierarchy": true
              }
            }
          },
          {
            "id": "57b9923e751d4b12",
            "type": "leaf",
            "state": {
              "type": "outline",
              "state": {
                "file": "development/python/╣╪╙┌▒╚╚№/Getting a token through the API.md"
              }
            }
          }
        ]
      }
    ],
    "direction": "horizontal",
    "width": 300,
    "collapsed": true
  },
  "left-ribbon": {
    "hiddenItems": {
      "switcher:打开快速切换": false,
      "graph:查看关系图谱": false,
      "canvas:新建白板": false,
      "daily-notes:打开/创建今天的日记": false,
      "templates:插入模板": false,
      "command-palette:打开命令面板": false
    }
  },
  "active": "fe4008cfb4e5ff88",
  "lastOpenFiles": [
    "development/git.md",
    "development/Development tools/Detail issues.md",
    "development/Development tools/vcpkg.md",
    "O&M/AWS/README.md",
    "development/╩¤╛▌╜с╣╣/┴┤▒э.md",
    "().md",
    "O&M/AWS/Host a static website.md",
    "O&M/AWS/┐╔┐┐╨╘.pdf",
    "O&M/AWS/Architecture.md",
    "O&M/AWS/Block Storage And Object Storage.md",
    "O&M/AWS/╟и╥╞╩¤╛▌┐т╡╜AWS RDS.md",
    "O&M/AWS/Static and dynamic websites.md",
    "O&M/AWS/╢п╠м═°╒╛.md",
    "O&M/AWS/╨з┬╩.pdf",
    "O&M/AWS/╫┐╘╜╘╦╙к.pdf",
    "O&M/AWS/░▓╚л╨╘.pdf",
    "O&M/AWS/Cost optimization.pdf",
    "O&M/AWS/Sustainability.pdf",
    "O&M/AWS/wellarchitected-framework.pdf",
    "O&M/Server/postgresql/Faqs.md",
    "O&M/Server/postgresql/Brief introduction.md",
    "O&M/Server/openstack/╣╪╙┌▒╚╚№/optimization.md",
    "O&M/Server/openstack/╣╪╙┌▒╚╚№/deploy.md"
  ]
}